competitions/__init__.py
competitions/api.py
competitions/app.py
competitions/compute_metrics.py
competitions/download.py
competitions/errors.py
competitions/evaluate.py
competitions/info.py
competitions/leaderboard.py
competitions/params.py
competitions/runner.py
competitions/submissions.py
competitions/text.py
competitions/utils.py
competitions/cli/__init__.py
competitions/cli/competitions.py
competitions/cli/create.py
competitions/cli/run.py
competitions/templates/index.html
competitions-0.1.6.data/data/templates/index.html
competitions-0.1.6.dist-info/LICENSE
competitions-0.1.6.dist-info/METADATA
competitions-0.1.6.dist-info/WHEEL
competitions-0.1.6.dist-info/entry_points.txt
competitions-0.1.6.dist-info/top_level.txt
competitions-0.1.6.dist-info/RECORD
