Metadata-Version: 2.1
Name: competitions
Version: 0.1.6
Summary: Hugging Face Competitions
Home-page: https://github.com/huggingface/competitions
Download-URL: https://github.com/huggingface/competitions/tags
Author: HuggingFace Inc.
License: Apache 2.0
Keywords: huggingface competitions machine learning ai nlp tabular
Classifier: Intended Audience :: Developers
Classifier: Intended Audience :: Education
Classifier: Intended Audience :: Science/Research
Classifier: License :: OSI Approved :: Apache Software License
Classifier: Operating System :: OS Independent
Classifier: Programming Language :: Python :: 3.10
Classifier: Topic :: Scientific/Engineering :: Artificial Intelligence
Requires-Python: >=3.10
License-File: LICENSE
Requires-Dist: fastapi ==0.108.0
Requires-Dist: joblib ==1.3.2
Requires-Dist: loguru ==0.7.2
Requires-Dist: pandas ==2.1.4
Requires-Dist: huggingface-hub ==0.20.2
Requires-Dist: tabulate ==0.9.0
Requires-Dist: markdown ==3.5.1
Requires-Dist: psutil ==5.9.0
Requires-Dist: python-multipart ==0.0.6
Requires-Dist: uvicorn ==0.22.0
Requires-Dist: py7zr ==0.20.6
Requires-Dist: pydantic ==2.5.3
Requires-Dist: hf-transfer
Requires-Dist: scikit-learn ==1.3.2
Requires-Dist: jiwer ==3.0.2
Requires-Dist: sacremoses ==0.0.53
Requires-Dist: sentencepiece ==0.1.99
Requires-Dist: xgboost ==1.7.6
Requires-Dist: nltk ==3.8.1
Requires-Dist: optuna ==3.3.0
Requires-Dist: einops ==0.6.1
Requires-Dist: peft ==0.7.1
Requires-Dist: trl ==0.7.4
Requires-Dist: tiktoken ==0.5.1
Requires-Dist: transformers ==4.36.1
Requires-Dist: accelerate ==0.25.0
Requires-Dist: diffusers ==0.21.4
Requires-Dist: bitsandbytes ==0.41.0
Requires-Dist: tqdm ==4.65.0
Provides-Extra: dev
Requires-Dist: black ~=23.0 ; extra == 'dev'
Requires-Dist: isort ==5.13.2 ; extra == 'dev'
Requires-Dist: flake8 ==7.0.0 ; extra == 'dev'
Requires-Dist: mypy ==1.8.0 ; extra == 'dev'
Provides-Extra: docs
Requires-Dist: black ~=23.0 ; extra == 'docs'
Requires-Dist: isort ==5.13.2 ; extra == 'docs'
Requires-Dist: flake8 ==7.0.0 ; extra == 'docs'
Requires-Dist: mypy ==1.8.0 ; extra == 'docs'
Requires-Dist: pytest ; extra == 'docs'
Requires-Dist: pytest-cov ; extra == 'docs'
Requires-Dist: hf-doc-builder ; extra == 'docs'
Provides-Extra: quality
Requires-Dist: black ~=23.0 ; extra == 'quality'
Requires-Dist: isort ==5.13.2 ; extra == 'quality'
Requires-Dist: flake8 ==7.0.0 ; extra == 'quality'
Requires-Dist: mypy ==1.8.0 ; extra == 'quality'
Provides-Extra: test
Requires-Dist: black ~=23.0 ; extra == 'test'
Requires-Dist: isort ==5.13.2 ; extra == 'test'
Requires-Dist: flake8 ==7.0.0 ; extra == 'test'
Requires-Dist: mypy ==1.8.0 ; extra == 'test'
Requires-Dist: pytest ; extra == 'test'
Requires-Dist: pytest-cov ; extra == 'test'
